README.rst
setup.cfg
setup.py
tigerhost/__init__.py
tigerhost/api_client.py
tigerhost/entry.py
tigerhost/settings.py
tigerhost/user.py
tigerhost/wsse.py
tigerhost.egg-info/PKG-INFO
tigerhost.egg-info/SOURCES.txt
tigerhost.egg-info/dependency_links.txt
tigerhost.egg-info/entry_points.txt
tigerhost.egg-info/requires.txt
tigerhost.egg-info/top_level.txt
tigerhost/commands/__init__.py
tigerhost/commands/access.py
tigerhost/commands/addons.py
tigerhost/commands/apps.py
tigerhost/commands/backends.py
tigerhost/commands/config.py
tigerhost/commands/domains.py
tigerhost/commands/git.py
tigerhost/commands/keys.py
tigerhost/commands/logs.py
tigerhost/commands/run_command.py
tigerhost/commands/user.py
tigerhost/utils/__init__.py
tigerhost/utils/decorators.py
tigerhost/vcs/__init__.py
tigerhost/vcs/base.py
tigerhost/vcs/git.py