Metadata-Version: 1.0
Name: tigerhost
Version: 0.6.0
Summary: TigerHost Command-Line Client
Home-page: https://github.com/naphatkrit/TigerHost
Author: Naphat Sanguansin
Author-email: naphat.krit@gmail.com
License: UNKNOWN
Platform: UNKNOWN
